mojeeb02/__init__.py
mojeeb02/app.py
mojeeb02-0.1.0.dist-info/METADATA
mojeeb02-0.1.0.dist-info/WHEEL
mojeeb02-0.1.0.dist-info/entry_points.txt
mojeeb02-0.1.0.dist-info/RECORD
