Metadata-Version: 2.4
Name: mojeeb02
Version: 0.1.0
Summary: My first python package developed by mojeeb
Requires-Python: >=3.10
